ai_core/__init__.py
ai_core/admin.py
ai_core/apps.py
ai_core/models.py
ai_core/plots.py
ai_core/tests.py
ai_core/tinyai.py
ai_core/urls.py
ai_core/views.py
ai_core/migrations/0001_initial.py
ai_core/migrations/0002_memorylink.py
ai_core/migrations/0003_memoryitem_context_tags_memoryitem_emotional_charge.py
ai_core/migrations/0004_memoryitem_embedding.py
ai_core/migrations/0005_activitylog.py
ai_core/migrations/__init__.py
tinyai_memory-0.1.10.dist-info/licenses/LICENSE
tinyai_memory-0.1.10.dist-info/METADATA
tinyai_memory-0.1.10.dist-info/WHEEL
tinyai_memory-0.1.10.dist-info/top_level.txt
tinyai_memory-0.1.10.dist-info/RECORD
