Metadata-Version: 2.4
Name: tinyai-memory
Version: 0.1.10
Summary: TinyAI: A Django-based neural memory and reasoning system
Author-email: Gerson De La Cruz <gdelacruz.developer@example.com>
License: TinyAI Memory Engine License
Classifier: Programming Language :: Python :: 3
Classifier: Framework :: Django
Classifier: Operating System :: OS Independent
Requires-Python: >=3.9
License-File: LICENSE
Requires-Dist: django>=4.2
Requires-Dist: numpy>=1.23
Requires-Dist: sentence-transformers>=2.2.2
Dynamic: license-file
